setup.py
dsnd_binomial_probability/Binomialdistribution_challenge.py
dsnd_binomial_probability/Gaussiandistribution.py
dsnd_binomial_probability/Generaldistribution.py
dsnd_binomial_probability/__init__.py
dsnd_binomial_probability.egg-info/PKG-INFO
dsnd_binomial_probability.egg-info/SOURCES.txt
dsnd_binomial_probability.egg-info/dependency_links.txt
dsnd_binomial_probability.egg-info/not-zip-safe
dsnd_binomial_probability.egg-info/top_level.txt