Metadata-Version: 1.0
Name: dsnd-binomial-probability
Version: 0.1
Summary: Binomial distributions
Home-page: UNKNOWN
Author: UNKNOWN
Author-email: UNKNOWN
License: UNKNOWN
Platform: UNKNOWN
